TerMPS/__init__.py
TerMPS/preprocessing_module.py
TerMPS-0.0.2.1.dist-info/LICENCE
TerMPS-0.0.2.1.dist-info/METADATA
TerMPS-0.0.2.1.dist-info/WHEEL
TerMPS-0.0.2.1.dist-info/entry_points.txt
TerMPS-0.0.2.1.dist-info/top_level.txt
TerMPS-0.0.2.1.dist-info/RECORD
