Metadata-Version: 2.1
Name: TerMPS
Version: 0.0.2.1
Summary: Preprocessing system for the TerM (INM RAS-MSU land surface model)
Author: A. Ryazanova, V. Bogomolov, M. Varentsov, A. Medvedev
Author-email: r.ann.1194@gmail.com
Maintainer: V. Stepanenko
Project-URL: Homepage, http://tesla.parallel.ru/Ryazanova/TerMPS
Project-URL: Documentations, http://tesla.parallel.ru/Ryazanova/TerMPS/-/wikis/home
Keywords: land surface data,aggregation,modeling
Classifier: Programming Language :: Python :: 3
Classifier: License :: OSI Approved :: MIT License
Classifier: Operating System :: OS Independent
Requires-Python: >=3.10
License-File: LICENCE
Requires-Dist: numpy >=1.23.5
Requires-Dist: xarray >=2023.1.0
Requires-Dist: netCDF4 >=1.6.2
